README.md
setup.py
dcn/__init__.py
dcn/client.py
dcn/handler.py
dcn/info.py
dcn/packet.py
dcn.egg-info/PKG-INFO
dcn.egg-info/SOURCES.txt
dcn.egg-info/dependency_links.txt
dcn.egg-info/requires.txt
dcn.egg-info/top_level.txt