Metadata-Version: 2.1
Name: dcn
Version: 2.0.0.4.1.1
Summary: Decentralized computer network
Home-page: https://github.com/draklowell/DCNLibrary
Author: Drak Lowell
License: Apache License 2.0
Platform: UNKNOWN
Classifier: Programming Language :: Python :: 3
Classifier: License :: OSI Approved :: MIT License
Classifier: Operating System :: OS Independent
Classifier: Development Status :: 4 - Beta
Classifier: Natural Language :: English
Requires-Python: >=3.8
